MANIFEST.in
README.txt
Readme.md
setup.py
simpledict.py
simpledict.egg-info/PKG-INFO
simpledict.egg-info/SOURCES.txt
simpledict.egg-info/dependency_links.txt
simpledict.egg-info/top_level.txt