Metadata-Version: 1.0
Name: simpledict
Version: 0.2.6
Summary: Simple dictionary wrapper
Home-page: http://github.com/robspychala/simpledict
Author: Robert Spychala
Author-email: robspychala@gmail.com
License: MIT
Keywords: dict,mongo
Platform: any
Classifier: Programming Language :: Python :: 2.6
Classifier: Programming Language :: Python :: 2.7
Classifier: Programming Language :: Python :: 3
Classifier: Development Status :: 3 - Alpha
Classifier: Topic :: Database :: Database Engines/Servers
Classifier: Topic :: Software Development :: Libraries :: Python Modules
Classifier: Intended Audience :: Developers
Classifier: License :: OSI Approved :: MIT License
Classifier: Operating System :: OS Independent
